LICENSE.txt
MANIFEST.in
README.md
setup.cfg
setup.py
apk_launch/__init__.py
apk_launch.egg-info/PKG-INFO
apk_launch.egg-info/SOURCES.txt
apk_launch.egg-info/dependency_links.txt
apk_launch.egg-info/top_level.txt
apk_launch/apk_analyzer/__init__.py
apk_launch/apk_analyzer/__main__.py
apk_launch/apk_analyzer/apkanalyzer.py
apk_launch/apk_launch/__init__.py
apk_launch/apk_launch/__main__.py
apk_launch/apk_launch/apklaunch.py
apk_launch/apk_stats/__init__.py
apk_launch/apk_stats/__main__.py
apk_launch/apk_stats/apkstats.py
apk_launch/utils/__init__.py
apk_launch/utils/apk_utils.py
apk_launch/utils/gradle_helper.py
apk_launch/utils/hbase_utils.py
apk_launch/utils/manifest_helper.py
apk_launch/utils/mycommand.py
apk_launch/utils/mythreadcommand.py
apk_launch/utils/parallel_utils.py
apk_launch/utils/tree_utils.py
scripts/apkanalyzer
scripts/apklaunch
scripts/apkstats
tests/__init__.py
tests/hashmap-armeabi-v7a-debug.apk
tests/test_apk_analyzer.py
tests/test_apk_launch.py
tests/test_apk_stats.py