Metadata-Version: 1.1
Name: apk-launch
Version: 0.4
Summary: Tools for performing various tasks on Android projects
Home-page: https://github.com/Zachout
Author: Zach Yannes
Author-email: zachyannes@gmail.com
License:                     GNU GENERAL PUBLIC LICENSE
